linzai_test1/__init__.py
linzai_test1/main.py
linzai_test1/model_util.py
tests/__init__.py
linzai_test1-1.0.2.dist-info/METADATA
linzai_test1-1.0.2.dist-info/WHEEL
linzai_test1-1.0.2.dist-info/top_level.txt
linzai_test1-1.0.2.dist-info/RECORD
