Metadata-Version: 2.1
Name: linzai-test1
Version: 1.0.2
Summary: xxxxx
Home-page: https://www.rockai.net
Author: zhangjl
Author-email: zhangjl@2345.com
Classifier: Development Status :: 3 - Alpha
Classifier: Intended Audience :: Developers
Classifier: Topic :: Software Development :: Build Tools
Classifier: License :: OSI Approved :: MIT License
Classifier: Programming Language :: Python :: 3.7
Classifier: Programming Language :: Python :: 3.8
Classifier: Programming Language :: Python :: 3.9
Requires-Python: >=3.7
